{"type":"FeatureCollection","name":"县名2","features":[{"type":"Feature","geometry":{"type":"Point","coordinates":[116.337598425,40.2150322305]},"properties":{"name":"昌平区","adcode":"110114","adcode_s":"1101","adcode_si":"11","dname":"北京市"}},{"type":"Feature","geometry":{"type":"Point","coordinates":[116.4133006555,39.6457052329]},"properties":{"name":"大兴区","adcode":"110115","adcode_s":"1101","adcode_si":"11","dname":"北京市"}},{"type":"Feature","geometry":{"type":"Point","coordinates":[116.4105803743,39.911032204]},"properties":{"name":"东城区","adcode":"110101","adcode_s":"1101","adcode_si":"11","dname":"北京市"}},{"type":"Feature","geometry":{"type":"Point","coordinates":[115.8481139855,39.7181491762]},"properties":{"name":"房山区","adcode":"110111","adcode_s":"1101","adcode_si":"11","dname":"北京市"}},{"type":"Feature","geometry":{"type":"Point","coordinates":[116.150588865,39.8256122225]},"properties":{"name":"丰台区","adcode":"110106","adcode_s":"1101","adcode_si":"11","dname":"北京市"}},{"type":"Feature","geometry":{"type":"Point","coordinates":[116.2271940492,40.0257074233]},"properties":{"name":"海淀区","adcode":"110108","adcode_s":"1101","adcode_si":"11","dname":"北京市"}},{"type":"Feature","geometry":{"type":"Point","coordinates":[116.4287636275,40.4039352752]},"properties":{"name":"怀柔区","adcode":"110116","adcode_s":"1101","adcode_si":"11","dname":"北京市"}},{"type":"Feature","geometry":{"type":"Point","coordinates":[115.79483799,40.0399723619]},"properties":{"name":"门头沟区","adcode":"110109","adcode_s":"1101","adcode_si":"11","dname":"北京市"}},{"type":"Feature","geometry":{"type":"Point","coordinates":[116.9873914452,40.5251204662]},"properties":{"name":"密云区","adcode":"110118","adcode_s":"1101","adcode_si":"11","dname":"北京市"}},{"type":"Feature","geometry":{"type":"Point","coordinates":[117.1380786259,40.2087408273]},"properties":{"name":"平谷区","adcode":"110117","adcode_s":"1101","adcode_si":"11","dname":"北京市"}},{"type":"Feature","geometry":{"type":"Point","coordinates":[116.1715650972,39.9317353966]},"properties":{"name":"石景山区","adcode":"110107","adcode_s":"1101","adcode_si":"11","dname":"北京市"}},{"type":"Feature","geometry":{"type":"Point","coordinates":[116.7171451461,40.1486806527]},"properties":{"name":"顺义区","adcode":"110113","adcode_s":"1101","adcode_si":"11","dname":"北京市"}},{"type":"Feature","geometry":{"type":"Point","coordinates":[116.3581882603,39.9113446488]},"properties":{"name":"西城区","adcode":"110102","adcode_s":"1101","adcode_si":"11","dname":"北京市"}},{"type":"Feature","geometry":{"type":"Point","coordinates":[116.1566585127,40.5366881019]},"properties":{"name":"延庆区","adcode":"110119","adcode_s":"1101","adcode_si":"11","dname":"北京市"}},{"type":"Feature","geometry":{"type":"Point","coordinates":[116.7281111853,39.8024889614]},"properties":{"name":"通州区","adcode":"110112","adcode_s":"1101","adcode_si":"11","dname":"北京市"}},{"type":"Feature","geometry":{"type":"Point","coordinates":[116.5075729246,39.9500976784]},"properties":{"name":"朝阳区","adcode":"110105","adcode_s":"1101","adcode_si":"11","dname":"北京市"}}]}