{"type":"FeatureCollection","name":"市名","features":[{"type":"Feature","geometry":{"type":"Point","coordinates":[102.6149973544,32.3984963737]},"properties":{"name":"阿坝藏族羌族自治州","adcode_s":"5132","adcode":"513200","个数":1,"adcode_si":"51","name_12":"四川省","adcode_1":"510000"}},{"type":"Feature","geometry":{"type":"Point","coordinates":[107.0381123753,32.0176976425]},"properties":{"name":"巴中市","adcode_s":"5119","adcode":"511900","个数":1,"adcode_si":"51","name_12":"四川省","adcode_1":"510000"}},{"type":"Feature","geometry":{"type":"Point","coordinates":[103.9296035738,30.6535486696]},"properties":{"name":"成都市","adcode_s":"5101","adcode":"510100","个数":1,"adcode_si":"51","name_12":"四川省","adcode_1":"510000"}},{"type":"Feature","geometry":{"type":"Point","coordinates":[107.644755019,31.3664816411]},"properties":{"name":"达州市","adcode_s":"5117","adcode":"511700","个数":1,"adcode_si":"51","name_12":"四川省","adcode_1":"510000"}},{"type":"Feature","geometry":{"type":"Point","coordinates":[104.4351980122,31.1295005479]},"properties":{"name":"德阳市","adcode_s":"5106","adcode":"510600","个数":1,"adcode_si":"51","name_12":"四川省","adcode_1":"510000"}},{"type":"Feature","geometry":{"type":"Point","coordinates":[99.9988715391,30.9467956357]},"properties":{"name":"甘孜藏族自治州","adcode_s":"5133","adcode":"513300","个数":1,"adcode_si":"51","name_12":"四川省","adcode_1":"510000"}},{"type":"Feature","geometry":{"type":"Point","coordinates":[106.663915926,30.4262976054]},"properties":{"name":"广安市","adcode_s":"5116","adcode":"511600","个数":1,"adcode_si":"51","name_12":"四川省","adcode_1":"510000"}},{"type":"Feature","geometry":{"type":"Point","coordinates":[105.7828251399,32.2613874929]},"properties":{"name":"广元市","adcode_s":"5108","adcode":"510800","个数":1,"adcode_si":"51","name_12":"四川省","adcode_1":"510000"}},{"type":"Feature","geometry":{"type":"Point","coordinates":[103.5705616317,29.2164676637]},"properties":{"name":"乐山市","adcode_s":"5111","adcode":"511100","个数":1,"adcode_si":"51","name_12":"四川省","adcode_1":"510000"}},{"type":"Feature","geometry":{"type":"Point","coordinates":[102.0799003766,27.8869393328]},"properties":{"name":"凉山彝族自治州","adcode_s":"5134","adcode":"513400","个数":1,"adcode_si":"51","name_12":"四川省","adcode_1":"510000"}},{"type":"Feature","geometry":{"type":"Point","coordinates":[105.45052986,28.5501313209]},"properties":{"name":"泸州市","adcode_s":"5105","adcode":"510500","个数":1,"adcode_si":"51","name_12":"四川省","adcode_1":"510000"}},{"type":"Feature","geometry":{"type":"Point","coordinates":[103.67612496,30.0793518209]},"properties":{"name":"眉山市","adcode_s":"5114","adcode":"511400","个数":1,"adcode_si":"51","name_12":"四川省","adcode_1":"510000"}},{"type":"Feature","geometry":{"type":"Point","coordinates":[104.702502765,31.8492029998]},"properties":{"name":"绵阳市","adcode_s":"5107","adcode":"510700","个数":1,"adcode_si":"51","name_12":"四川省","adcode_1":"510000"}},{"type":"Feature","geometry":{"type":"Point","coordinates":[106.2035626832,31.1954525848]},"properties":{"name":"南充市","adcode_s":"5113","adcode":"511300","个数":1,"adcode_si":"51","name_12":"四川省","adcode_1":"510000"}},{"type":"Feature","geometry":{"type":"Point","coordinates":[104.9106381508,29.6409919365]},"properties":{"name":"内江市","adcode_s":"5110","adcode":"511000","个数":1,"adcode_si":"51","name_12":"四川省","adcode_1":"510000"}},{"type":"Feature","geometry":{"type":"Point","coordinates":[101.7296476742,26.8076368152]},"properties":{"name":"攀枝花市","adcode_s":"5104","adcode":"510400","个数":1,"adcode_si":"51","name_12":"四川省","adcode_1":"510000"}},{"type":"Feature","geometry":{"type":"Point","coordinates":[105.4714680519,30.6320606492]},"properties":{"name":"遂宁市","adcode_s":"5109","adcode":"510900","个数":1,"adcode_si":"51","name_12":"四川省","adcode_1":"510000"}},{"type":"Feature","geometry":{"type":"Point","coordinates":[102.663966428,29.9129286]},"properties":{"name":"雅安市","adcode_s":"5118","adcode":"511800","个数":1,"adcode_si":"51","name_12":"四川省","adcode_1":"510000"}},{"type":"Feature","geometry":{"type":"Point","coordinates":[104.634804833,28.5736044874]},"properties":{"name":"宜宾市","adcode_s":"5115","adcode":"511500","个数":1,"adcode_si":"51","name_12":"四川省","adcode_1":"510000"}},{"type":"Feature","geometry":{"type":"Point","coordinates":[105.115662967,30.1002673098]},"properties":{"name":"资阳市","adcode_s":"5120","adcode":"512000","个数":1,"adcode_si":"51","name_12":"四川省","adcode_1":"510000"}},{"type":"Feature","geometry":{"type":"Point","coordinates":[104.9643280313,29.2233999662]},"properties":{"name":"自贡市","adcode_s":"5103","adcode":"510300","个数":1,"adcode_si":"51","name_12":"四川省","adcode_1":"510000"}}]}