{"type":"FeatureCollection","name":"市名","features":[{"type":"Feature","geometry":{"type":"Point","coordinates":[119.1600612773,26.0636614405]},"properties":{"name":"福州市","adcode_s":"3501","adcode":"350100","个数":1,"adcode_si":"35","name_12":"福建省","adcode_1":"350000"}},{"type":"Feature","geometry":{"type":"Point","coordinates":[116.7404218862,25.293052683]},"properties":{"name":"龙岩市","adcode_s":"3508","adcode":"350800","个数":1,"adcode_si":"35","name_12":"福建省","adcode_1":"350000"}},{"type":"Feature","geometry":{"type":"Point","coordinates":[118.1433734013,27.3389469198]},"properties":{"name":"南平市","adcode_s":"3507","adcode":"350700","个数":1,"adcode_si":"35","name_12":"福建省","adcode_1":"350000"}},{"type":"Feature","geometry":{"type":"Point","coordinates":[119.4698038372,26.9770965605]},"properties":{"name":"宁德市","adcode_s":"3509","adcode":"350900","个数":1,"adcode_si":"35","name_12":"福建省","adcode_1":"350000"}},{"type":"Feature","geometry":{"type":"Point","coordinates":[118.8827837274,25.4532766694]},"properties":{"name":"莆田市","adcode_s":"3503","adcode":"350300","个数":1,"adcode_si":"35","name_12":"福建省","adcode_1":"350000"}},{"type":"Feature","geometry":{"type":"Point","coordinates":[118.2589210401,25.2093797353]},"properties":{"name":"泉州市","adcode_s":"3505","adcode":"350500","个数":1,"adcode_si":"35","name_12":"福建省","adcode_1":"350000"}},{"type":"Feature","geometry":{"type":"Point","coordinates":[117.3976638484,26.2988833725]},"properties":{"name":"三明市","adcode_s":"3504","adcode":"350400","个数":1,"adcode_si":"35","name_12":"福建省","adcode_1":"350000"}},{"type":"Feature","geometry":{"type":"Point","coordinates":[118.118934448,24.7392294708]},"properties":{"name":"厦门市","adcode_s":"3502","adcode":"350200","个数":1,"adcode_si":"35","name_12":"福建省","adcode_1":"350000"}},{"type":"Feature","geometry":{"type":"Point","coordinates":[117.4421646701,24.3778025623]},"properties":{"name":"漳州市","adcode_s":"3506","adcode":"350600","个数":1,"adcode_si":"35","name_12":"福建省","adcode_1":"350000"}}]}